{"title": "适用苹果11手机壳iPhone11保护套2021年新款ip11软硅胶ipone", "image": "https://cbu01.alicdn.com/img/ibank/O1CN01XvZqiv2KExhnmpyl5_!!2214687799526-0-cib.jpg", "images": ["https://cbu01.alicdn.com/img/ibank/O1CN01XvZqiv2KExhnmpyl5_!!2214687799526-0-cib.jpg", "https://cbu01.alicdn.com/img/ibank/O1CN01L9FBV52KExheRsggW_!!2214687799526-0-cib.jpg", "https://cbu01.alicdn.com/img/ibank/O1CN01hOUlUP2KExhkf4TJY_!!2214687799526-0-cib.jpg", "https://cbu01.alicdn.com/img/ibank/O1CN017JU35U2KExheRtctw_!!2214687799526-0-cib.jpg", "https://cbu01.alicdn.com/img/ibank/O1CN01UNUvOx2KExhvxpbX8_!!2214687799526-0-cib.jpg"], "priceLow": 0.19, "priceHigh": 0.25, "priceCNY": {"low": 1.4, "high": 1.8}, "moq": 1, "itemUrl": "https://detail.1688.com/offer/685469710262.html", "specs": [{"name": "材质", "value": "tpu"}, {"name": "工艺", "value": "磨砂"}, {"name": "风格", "value": "简约风"}], "unit": "件", "offerId": "685469710262", "return7day": "OK", "sold": 657, "wantBuyCount": 33, "badgeLabels": [{"label": "免费拿样", "class": "green"}, {"label": "买家保障", "class": "gold"}, {"label": "跨境专供", "class": "blue"}, {"label": "批发价", "class": "green"}, {"label": "支持混批", "class": "green"}, {"label": "品质不符包赔", "class": "green"}, {"label": "7天无理由退货", "class": "green"}, {"label": "严选晚发必赔", "class": "green"}], "supplierName": "东莞市虎门清运货运代理服务部", "shop_rate": null, "shop_years": 4, "repurchase": null, "shippingLocation": "广东汕头", "industryCluster": "", "deliveryDays": 2, "freeSample": false, "sellerType": "normal", "sellerTypeLabel": "普通商家", "factoryFlags": "非生产厂家", "certType": null, "certReportUrl": null, "rankText": "", "sellerTierLabel": "贸易商", "repeatBuyers": "", "crossBorderBuyers": "", "skus": [{"name": "苹果11【石墨黑】", "imgUrl": "https://cbu01.alicdn.com/img/ibank/O1CN01erqJKP2KExhrAKstd_!!2214687799526-0-cib.jpg"}, {"name": "苹果11【古董白】", "imgUrl": "https://cbu01.alicdn.com/img/ibank/O1CN01DpnNGH2KExhoR4EBs_!!2214687799526-0-cib.jpg"}, {"name": "苹果11【暗夜绿】", "imgUrl": "https://cbu01.alicdn.com/img/ibank/O1CN01jMINXB2KExhpuODH6_!!2214687799526-0-cib.jpg"}, {"name": "苹果11【薰衣灰】", "imgUrl": "https://cbu01.alicdn.com/img/ibank/O1CN01OVCxCj2KExhsqTXVM_!!2214687799526-0-cib.jpg"}, {"name": "苹果11【山茶红】", "imgUrl": "https://cbu01.alicdn.com/img/ibank/O1CN01nl6s3T2KExhvxqH9H_!!2214687799526-0-cib.jpg"}, {"name": "苹果11【草紫色】", "imgUrl": "https://cbu01.alicdn.com/img/ibank/O1CN01cn9PGM2KExhk07FyO_!!2214687799526-0-cib.jpg"}], "price_tiers": [{"qty_min": 1, "qty_max": 499, "unit_price": 1.8}, {"qty_min": 500, "qty_max": 999, "unit_price": 1.6}, {"qty_min": 1000, "qty_max": null, "unit_price": 1.4}], "verdict_product": "⚠️ 缺认证 — 销量 657+ 但无验厂认证，¥11 拿样就能确认品质", "verdict_factory": "⚠️ 非工厂 — 贸易商从第三方拿货，价差可能大，先拿样比对", "verdict_sample": "① 付定金 → ② 验货照片 → ③ 付尾款 → ④ 发货", "dataTier": "partial", "dataTierReason": "无工厂认证，经营 1 年以上 · 建议拿样验证", "shopUrl": ""}